mySUNI/__init__.py
mySUNI/cds.py
mySUNI/skada.py
mySUNI/utils.py
mysuni-2.0.6.dist-info/licenses/LICENSE
mysuni-2.0.6.dist-info/METADATA
mysuni-2.0.6.dist-info/WHEEL
mysuni-2.0.6.dist-info/top_level.txt
mysuni-2.0.6.dist-info/RECORD
