Metadata-Version: 2.4
Name: mySUNI
Version: 2.0.6
Summary: mySUNI CDS - 데이터 과학 교육용 라이브러리
Home-page: https://github.com/braincrew/cds
Author: BAEM1N, Teddy Lee
Author-email: BAEM1N <baemin.dev@gmail.com>, Teddy Lee <teddylee777@gmail.com>
Maintainer-email: BAEM1N <baemin.dev@gmail.com>
License: MIT License
Project-URL: Homepage, https://github.com/braincrew/cds
Project-URL: Repository, https://github.com/braincrew/cds
Project-URL: Documentation, https://github.com/braincrew/cds/wiki
Project-URL: Bug Reports, https://github.com/braincrew/cds/issues
Keywords: mySUNI,CDS,data science,education,machine learning
Classifier: Development Status :: 4 - Beta
Classifier: Intended Audience :: Education
Classifier: Topic :: Scientific/Engineering :: Artificial Intelligence
Classifier: License :: OSI Approved :: MIT License
Classifier: Programming Language :: Python :: 3
Classifier: Programming Language :: Python :: 3.7
Classifier: Programming Language :: Python :: 3.8
Classifier: Programming Language :: Python :: 3.9
Classifier: Programming Language :: Python :: 3.10
Classifier: Programming Language :: Python :: 3.11
Requires-Python: >=3.7
License-File: LICENSE
Requires-Dist: tqdm
Requires-Dist: scikit-learn
Requires-Dist: pandas
Requires-Dist: matplotlib
Requires-Dist: seaborn
Requires-Dist: jupyter
Requires-Dist: ipywidgets
Requires-Dist: requests
Requires-Dist: numpy
Provides-Extra: dev
Requires-Dist: pytest; extra == "dev"
Requires-Dist: pytest-cov; extra == "dev"
Requires-Dist: black; extra == "dev"
Requires-Dist: flake8; extra == "dev"
Requires-Dist: twine; extra == "dev"
Requires-Dist: wheel; extra == "dev"
Requires-Dist: build; extra == "dev"
Provides-Extra: test
Requires-Dist: pytest; extra == "test"
Requires-Dist: pytest-cov; extra == "test"
Dynamic: author
Dynamic: home-page
Dynamic: license-file
Dynamic: requires-python
